training_pipeline/README.md
training_pipeline/best_config.py
training_pipeline/configs/__init__.py
training_pipeline/configs/gridsearch.py
training_pipeline/data.py
training_pipeline/hyperparameter_tuning.py
training_pipeline/models.py
training_pipeline/settings.py
training_pipeline/train.py
training_pipeline/transformers.py
training_pipeline/utils.py
mip_training_pipeline-0.1.0.dist-info/METADATA
mip_training_pipeline-0.1.0.dist-info/WHEEL
mip_training_pipeline-0.1.0.dist-info/RECORD
